AUTHORS
LICENSE
LICENSES
MANIFEST.in
README.rst
setup.py
django_filer_pdf.egg-info/PKG-INFO
django_filer_pdf.egg-info/SOURCES.txt
django_filer_pdf.egg-info/dependency_links.txt
django_filer_pdf.egg-info/not-zip-safe
django_filer_pdf.egg-info/requires.txt
django_filer_pdf.egg-info/top_level.txt
filer_pdf/__init__.py
filer_pdf/admin.py
filer_pdf/models.py
filer_pdf/tests.py
filer_pdf/views.py
filer_pdf/migrations/0001_initial.py
filer_pdf/migrations/__init__.py
filer_pdf/static/filer/icons/pdf_128x128.png
filer_pdf/static/filer/icons/pdf_16x16.png
filer_pdf/static/filer/icons/pdf_32x32.png
filer_pdf/static/filer/icons/pdf_48x48.png
filer_pdf/static/filer/icons/pdf_64x64.png