Metadata-Version: 1.1
Name: django-filer-pdf
Version: 0.0.1
Summary: A django-filer plugin for PDF file support.
Home-page: https://github.com/phihos/django-filer-pdf
Author: Philipp Hossner
Author-email: philipp.hossner@posteo.de
License: BSD
Platform: OS Independent
Classifier: Development Status :: 4 - Beta
Classifier: Framework :: Django
Classifier: Intended Audience :: Developers
Classifier: License :: OSI Approved :: BSD License
Classifier: Operating System :: OS Independent
Classifier: Programming Language :: Python
Classifier: Topic :: Internet :: WWW/HTTP
Classifier: Programming Language :: Python :: 2.6
Classifier: Programming Language :: Python :: 2.7
Classifier: Programming Language :: Python :: 3.3
Classifier: Programming Language :: Python :: 3.4
